{
    "__comment": {
        "wa": "wing area (m^2)",
        "engine_thr": "reference engiune thrust (N)",
        "mmo": "mach, max operating",
        "mtow": "max take-oof weight (kg)",
        "mlw": "max landing weight (kg)",
        "zfw": "zero fuel weight, max (kg)",
        "oew": "operating empty weight (kg)",
        "mfc": "max fuel capacity (L)",
        "ref": "reference links"
    },
    "A320": {
        "n_engines": 2,
        "engine_thr": 140000.0,
        "wa": 122.6,
        "mmo": 0.82,
        "mtow": 78000.0,
        "mlw": 66000.0,
        "zfw": 62500.0,
        "oew": 42600.0,
        "mfc": 24210.0,
        "engines": ["CFM56-5A1","CFM56-5A3", "CFM56-5B4", "CFM56-5B6", "V2500-A1", "V2527-A5"],
        "ref": "https://en.wikipedia.org/wiki/Airbus_A380"
    }, 
    "A343": {
        "n_engines": 4,
        "engine_thr": 151000.0,
        "wa": 361.6,
        "mmo": 0.86,
        "mtow": 276000.0,
        "mlw": 190000.0,
        "zfw": 178000.0,
        "oew": 130000.0,
        "mfc": 147000.0,
        "engines": ["CFM56-5C2", "CFM56-5C3", "CFM56-5C4"],
        "ref": "https://en.wikipedia.org/wiki/Airbus_A340"
    }, 
    "A346": {
        "n_engines": 4,
        "engine_thr": 275000.0,
        "wa": 439.4,
        "mmo": 0.86,
        "mtow": 368000.0,
        "mlw": 254000.0,
        "zfw": 240000.0,
        "oew": 177000.0,
        "mfc": 195000.0,
        "engines": ["Trent 556-61", "Trent 556A2-61"],
        "ref": "https://en.wikipedia.org/wiki/Airbus_A340"
    }, 
    "A388": {
        "n_engines": 4,
        "engine_thr": 310000.0,
        "wa": 845.0,
        "mmo": 0.89,
        "mtow": 575000.0,
        "mlw": 394000.0,
        "zfw": 369000.0,
        "oew": 369000.0,
        "mfc": 323546.0,
        "engines": ["GP7270", "GP7272", "Trent 970", "Trent 972"],
        "ref": "https://en.wikipedia.org/wiki/Airbus_A320"
    }, 
    "B738": {
        "n_engines": 2,
        "engine_thr": 147000.0,
        "wa": 124.6,
        "mmo": 0.82,
        "mtow": 78000.0,
        "mlw": 65000.0,
        "zfw": 62000.0,
        "oew": 41000.0,
        "mfc": 26000.0,
        "engines": ["CFM56-7B24", "CFM56-7B26", "CFM56-7B27"],
        "ref": "https://en.wikipedia.org/wiki/Boeing_727"
    }, 
    "B772": {
        "n_engines": 2,
        "engine_thr": 342000.0,
        "wa": 427.8,
        "mmo": 0.87,
        "mtow": 297000.0,
        "mlw": 213000.0,
        "zfw": 190000.0,
        "oew": 138000.0,
        "mfc": 171000.0,
        "engines": ["PW4077", "Trent 877", "GE90-77B", "PW4090", "Trent 895", "GE90-94B"],
        "ref": "https://en.wikipedia.org/wiki/Boeing_777"
    }, 
    "B788": {
        "n_engines": 2,
        "engine_thr": 280000.0,
        "wa": 325,
        "mmo": 0.90,
        "mtow": 228000.0,
        "mlw": 172000.0,
        "zfw": 161000.0,
        "oew": 118000.0,
        "mfc": 126210.0,
        "engines": ["GEnx-1B58", "GEnx-1B64", "GEnx-1B67", "GEnx-1B70", "GEnx-2B67"],
        "ref": "https://en.wikipedia.org/wiki/Boeing_787_Dreamliner"
    }, 
    "B789": {
        "n_engines": 2,
        "engine_thr": 320000.0,
        "wa": 325,
        "mmo": 0.90,
        "mtow": 253000.0,
        "mlw": 193000.0,
        "zfw": 181000.0,
        "oew": 126000.0,
        "mfc": 126370.0,
        "engines": ["GEnx-1B64", "GEnx-1B67", "GEnx-1B70"],
        "ref": "https://en.wikipedia.org/wiki/Boeing_787_Dreamliner"
    }
}